CHANGES.txt
COPYRIGHT.txt
LICENSE.txt
rudolf.py
setup.cfg
setup.py
test_rudolf.rst
rudolf.egg-info/PKG-INFO
rudolf.egg-info/SOURCES.txt
rudolf.egg-info/dependency_links.txt
rudolf.egg-info/entry_points.txt
rudolf.egg-info/requires.txt
rudolf.egg-info/top_level.txt
rudolf.egg-info/zip-safe
test-support/failing/failing_doctest.rst
test-support/failing/failing_doctest_with_ndiff.rst
test-support/failing/failing_tests.py
test-support/passing/passing_doctest.rst
test-support/passing/passing_tests.py
