Metadata-Version: 1.0
Name: rudolf
Version: 0.2a
Summary: Colour output plugin for the nose testing framework
Home-page: http://pypi.python.org/pypi/rudolf/
Author: John J. Lee
Author-email: jjl@pobox.com
License: ZPL 2.1
Download-URL: http://pypi.python.org/pypi/rudolf/
Platform: POSIX
